LICENSE
MANIFEST.in
README.md
setup.py
microstarter.egg-info/PKG-INFO
microstarter.egg-info/SOURCES.txt
microstarter.egg-info/dependency_links.txt
microstarter.egg-info/entry_points.txt
microstarter.egg-info/requires.txt
microstarter.egg-info/top_level.txt
startmicro/__init__.py
startmicro/conf/__init__.py
startmicro/conf/docker.py
startmicro/conf/dotenv.py
startmicro/conf/exaples.py
startmicro/conf/readme.py
startmicro/conf/requirements.py
startmicro/conf/run.py
startmicro/conf/app/__init__.py
startmicro/conf/app/api.py
startmicro/conf/app/app.py
startmicro/conf/app/utils.py
startmicro/conf/instance_py/__init__.py
startmicro/conf/instance_py/config.py
startmicro/core/__init__.py
startmicro/core/base.py
startmicro/core/command.py
startmicro/core/management.py
startmicro/core/utils/__init__.py
startmicro/core/utils/color.py
startmicro/core/utils/detect.py
startmicro/core/utils/questions.py
startmicro/core/utils/termcolors.py
startmicro/script/__init__.py
startmicro/script/start_micro.py
startmicro/utils/__init__.py
startmicro/utils/version.py