Metadata-Version: 2.1
Name: microstarter
Version: 0.0.6
Summary: Microservice simple Starter Flask example
Home-page: https://github.com/munisisazade/startmicro
Author: Munis Isazade
Author-email: munisisazade@gmail.com
License: MIT
Platform: any
Classifier: Intended Audience :: Developers
Classifier: Programming Language :: Python
Classifier: Programming Language :: Python :: 3.5
Classifier: Programming Language :: Python :: 3.6
Classifier: Programming Language :: Python :: 3.7
Classifier: Programming Language :: Python :: 3 :: Only
Classifier: License :: OSI Approved :: MIT License
Classifier: Operating System :: OS Independent
Provides-Extra: prompt_toolkit
